{
  "presentation": "Ascites",
  "items": [
    {
      "name": "Cirrhosis",
      "system": "HEPATIC",
      "redFlag": false,
      "symptoms": {
        "onset": [],
        "progression": [],
        "palliate": [],
        "provoke": [],
        "quality": [],
        "timing": [],
        "region": [],
        "radiation": [],
        "severity": [],
        "clinical tests": [],
        "other symptoms": []
      },
      "freq": "common"
    },
    {
      "name": "Hepatic tumours",
      "system": "HEPATIC",
      "redFlag": false,
      "symptoms": {
        "onset": [],
        "progression": [],
        "palliate": [],
        "provoke": [],
        "quality": [],
        "timing": [],
        "region": [],
        "radiation": [],
        "severity": [],
        "clinical tests": [],
        "other symptoms": []
      },
      "freq": "uncommon"
    },
    {
      "name": "Peritoneal metastases",
      "system": "MALIGNANT DISEASE",
      "redFlag": false,
      "symptoms": {
        "onset": [],
        "progression": [],
        "palliate": [],
        "provoke": [],
        "quality": [],
        "timing": [],
        "region": [],
        "radiation": [],
        "severity": [],
        "clinical tests": [],
        "other symptoms": []
      },
      "freq": "common"
    },
    {
      "name": "Abdominal/pelvic tumour (primary or secondary)",
      "system": "MALIGNANT DISEASE",
      "redFlag": false,
      "symptoms": {
        "onset": [],
        "progression": [],
        "palliate": [],
        "provoke": [],
        "quality": [],
        "timing": [],
        "region": [],
        "radiation": [],
        "severity": [],
        "clinical tests": [],
        "other symptoms": []
      },
      "freq": "common"
    },
    {
      "name": "Pseudomyxoma peritonei",
      "system": "MALIGNANT DISEASE",
      "redFlag": false,
      "symptoms": {
        "onset": [],
        "progression": [],
        "palliate": [],
        "provoke": [],
        "quality": [],
        "timing": [],
        "region": [],
        "radiation": [],
        "severity": [],
        "clinical tests": [],
        "other symptoms": []
      },
      "freq": "rare"
    },
    {
      "name": "Primary mesothelioma",
      "system": "MALIGNANT DISEASE",
      "redFlag": false,
      "symptoms": {
        "onset": [],
        "progression": [],
        "palliate": [],
        "provoke": [],
        "quality": [],
        "timing": [],
        "region": [],
        "radiation": [],
        "severity": [],
        "clinical tests": [],
        "other symptoms": []
      },
      "freq": "rare"
    },
    {
      "name": "Cardiac failure",
      "system": "CARDIAC",
      "redFlag": false,
      "symptoms": {
        "onset": [],
        "progression": [],
        "palliate": [],
        "provoke": [],
        "quality": [],
        "timing": [],
        "region": [],
        "radiation": [],
        "severity": [],
        "clinical tests": [],
        "other symptoms": []
      },
      "freq": "common"
    },
    {
      "name": "Nephrotic syndrome",
      "system": "CARDIAC",
      "redFlag": false,
      "symptoms": {
        "onset": [],
        "progression": [],
        "palliate": [],
        "provoke": [],
        "quality": [],
        "timing": [],
        "region": [],
        "radiation": [],
        "severity": [],
        "clinical tests": [],
        "other symptoms": []
      },
      "freq": "common"
    },
    {
      "name": "TB",
      "system": "PERITONITIS",
      "redFlag": false,
      "symptoms": {
        "onset": [],
        "progression": [],
        "palliate": [],
        "provoke": [],
        "quality": [],
        "timing": [],
        "region": [],
        "radiation": [],
        "severity": [],
        "clinical tests": [],
        "other symptoms": []
      },
      "freq": "uncommon"
    },
    {
      "name": "Spontaneous bacterial",
      "system": "PERITONITIS",
      "redFlag": false,
      "symptoms": {
        "onset": [],
        "progression": [],
        "palliate": [],
        "provoke": [],
        "quality": [],
        "timing": [],
        "region": [],
        "radiation": [],
        "severity": [],
        "clinical tests": [],
        "other symptoms": []
      },
      "freq": "uncommon"
    },
    {
      "name": "Budd\u2013Chiari syndrome",
      "system": "VENOUS OBSTRUCTION",
      "redFlag": false,
      "symptoms": {
        "onset": [],
        "progression": [],
        "palliate": [],
        "provoke": [],
        "quality": [],
        "timing": [],
        "region": [],
        "radiation": [],
        "severity": [],
        "clinical tests": [],
        "other symptoms": []
      },
      "freq": "rare"
    },
    {
      "name": "Veno-occlusive disease",
      "system": "VENOUS OBSTRUCTION",
      "redFlag": false,
      "symptoms": {
        "onset": [],
        "progression": [],
        "palliate": [],
        "provoke": [],
        "quality": [],
        "timing": [],
        "region": [],
        "radiation": [],
        "severity": [],
        "clinical tests": [],
        "other symptoms": []
      },
      "freq": "rare"
    },
    {
      "name": "Hepatic portal vein obstruction",
      "system": "VENOUS OBSTRUCTION",
      "redFlag": false,
      "symptoms": {
        "onset": [],
        "progression": [],
        "palliate": [],
        "provoke": [],
        "quality": [],
        "timing": [],
        "region": [],
        "radiation": [],
        "severity": [],
        "clinical tests": [],
        "other symptoms": []
      },
      "freq": "rare"
    },
    {
      "name": "Inferior vena cava obstruction",
      "system": "VENOUS OBSTRUCTION",
      "redFlag": false,
      "symptoms": {
        "onset": [],
        "progression": [],
        "palliate": [],
        "provoke": [],
        "quality": [],
        "timing": [],
        "region": [],
        "radiation": [],
        "severity": [],
        "clinical tests": [],
        "other symptoms": []
      },
      "freq": "rare"
    },
    {
      "name": "Pancreatitis",
      "system": "Gastrointestinal",
      "redFlag": false,
      "symptoms": {
        "onset": [],
        "progression": [],
        "palliate": [],
        "provoke": [],
        "quality": [],
        "timing": [],
        "region": [],
        "radiation": [],
        "severity": [],
        "clinical tests": [],
        "other symptoms": []
      },
      "freq": "uncommon"
    },
    {
      "name": "Malabsorption",
      "system": "Gastrointestinal",
      "redFlag": false,
      "symptoms": {
        "onset": [],
        "progression": [],
        "palliate": [],
        "provoke": [],
        "quality": [],
        "timing": [],
        "region": [],
        "radiation": [],
        "severity": [],
        "clinical tests": [],
        "other symptoms": []
      },
      "freq": "uncommon"
    },
    {
      "name": "Bile ascites",
      "system": "Gastrointestinal",
      "redFlag": false,
      "symptoms": {
        "onset": [],
        "progression": [],
        "palliate": [],
        "provoke": [],
        "quality": [],
        "timing": [],
        "region": [],
        "radiation": [],
        "severity": [],
        "clinical tests": [],
        "other symptoms": []
      },
      "freq": "uncommon"
    }
  ],
  "sources": {
    "index_keys": [
      "Ascites"
    ],
    "index_type": "clinical"
  },
  "symptoms": {}
}