{
  "presentation": "Gait abnormalities",
  "items": [
    {
      "name": "Pain \u2013 antalgic gait",
      "system": "STRUCTURAL",
      "redFlag": false,
      "symptoms": {
        "onset": [],
        "progression": [],
        "palliate": [],
        "provoke": [],
        "quality": [],
        "timing": [],
        "region": [],
        "radiation": [],
        "severity": [],
        "clinical tests": [],
        "other symptoms": []
      },
      "freq": "common"
    },
    {
      "name": "Length discrepancies \u2013 short leg gait",
      "system": "STRUCTURAL",
      "redFlag": false,
      "symptoms": {
        "onset": [],
        "progression": [],
        "palliate": [],
        "provoke": [],
        "quality": [],
        "timing": [],
        "region": [],
        "radiation": [],
        "severity": [],
        "clinical tests": [],
        "other symptoms": []
      },
      "freq": "common"
    },
    {
      "name": "Weak hip abductors \u2013 Trendelenburg or waddling gait",
      "system": "STRUCTURAL",
      "redFlag": false,
      "symptoms": {
        "onset": [],
        "progression": [],
        "palliate": [],
        "provoke": [],
        "quality": [],
        "timing": [],
        "region": [],
        "radiation": [],
        "severity": [],
        "clinical tests": [],
        "other symptoms": []
      },
      "freq": "uncommon"
    },
    {
      "name": "Femoral anteversion \u2013 intoe gait",
      "system": "STRUCTURAL",
      "redFlag": false,
      "symptoms": {
        "onset": [],
        "progression": [],
        "palliate": [],
        "provoke": [],
        "quality": [],
        "timing": [],
        "region": [],
        "radiation": [],
        "severity": [],
        "clinical tests": [],
        "other symptoms": []
      },
      "freq": "uncommon"
    },
    {
      "name": "Stroke \u2013 hemiplegic gait",
      "system": "NEUROLOGICAL",
      "redFlag": false,
      "symptoms": {
        "onset": [],
        "progression": [],
        "palliate": [],
        "provoke": [],
        "quality": [],
        "timing": [],
        "region": [],
        "radiation": [],
        "severity": [],
        "clinical tests": [],
        "other symptoms": []
      },
      "freq": "common"
    },
    {
      "name": "Parkinson\u2019s disease \u2013 festinant gait",
      "system": "NEUROLOGICAL",
      "redFlag": false,
      "symptoms": {
        "onset": [],
        "progression": [],
        "palliate": [],
        "provoke": [],
        "quality": [],
        "timing": [],
        "region": [],
        "radiation": [],
        "severity": [],
        "clinical tests": [],
        "other symptoms": []
      },
      "freq": "common"
    },
    {
      "name": "Multiple sclerosis \u2013 scissoring gait",
      "system": "NEUROLOGICAL",
      "redFlag": false,
      "symptoms": {
        "onset": [],
        "progression": [],
        "palliate": [],
        "provoke": [],
        "quality": [],
        "timing": [],
        "region": [],
        "radiation": [],
        "severity": [],
        "clinical tests": [],
        "other symptoms": []
      },
      "freq": "common"
    },
    {
      "name": "Peripheral neuropathy \u2013 sensory ataxia",
      "system": "NEUROLOGICAL",
      "redFlag": false,
      "symptoms": {
        "onset": [],
        "progression": [],
        "palliate": [],
        "provoke": [],
        "quality": [],
        "timing": [],
        "region": [],
        "radiation": [],
        "severity": [],
        "clinical tests": [],
        "other symptoms": []
      },
      "freq": "uncommon"
    },
    {
      "name": "Cerebellar disease \u2013 cerebellar ataxia",
      "system": "NEUROLOGICAL",
      "redFlag": false,
      "symptoms": {
        "onset": [],
        "progression": [],
        "palliate": [],
        "provoke": [],
        "quality": [],
        "timing": [],
        "region": [],
        "radiation": [],
        "severity": [],
        "clinical tests": [],
        "other symptoms": []
      },
      "freq": "uncommon"
    },
    {
      "name": "Peroneal nerve palsy \u2013 foot drop gait",
      "system": "NEUROLOGICAL",
      "redFlag": false,
      "symptoms": {
        "onset": [],
        "progression": [],
        "palliate": [],
        "provoke": [],
        "quality": [],
        "timing": [],
        "region": [],
        "radiation": [],
        "severity": [],
        "clinical tests": [],
        "other symptoms": []
      },
      "freq": "uncommon"
    },
    {
      "name": "Cerebral palsy \u2013 scissoring gait",
      "system": "NEUROLOGICAL",
      "redFlag": false,
      "symptoms": {
        "onset": [],
        "progression": [],
        "palliate": [],
        "provoke": [],
        "quality": [],
        "timing": [],
        "region": [],
        "radiation": [],
        "severity": [],
        "clinical tests": [],
        "other symptoms": []
      },
      "freq": "uncommon"
    },
    {
      "name": "Frontal lobe lesions \u2013 apraxic gait",
      "system": "NEUROLOGICAL",
      "redFlag": false,
      "symptoms": {
        "onset": [],
        "progression": [],
        "palliate": [],
        "provoke": [],
        "quality": [],
        "timing": [],
        "region": [],
        "radiation": [],
        "severity": [],
        "clinical tests": [],
        "other symptoms": []
      },
      "freq": "rare"
    }
  ],
  "sources": {
    "index_keys": [
      "Gait abnormalities"
    ],
    "index_type": "clinical"
  },
  "symptoms": {}
}