{
  "presentation": "Scrotal pain",
  "items": [
    {
      "name": "Infected sebaceous cyst",
      "system": "General",
      "redFlag": false,
      "hpi": {
        "onset": [],
        "progression": [],
        "palliate": [],
        "provoke": [],
        "quality": [],
        "timing": [],
        "region": [],
        "radiation": [],
        "severity": [],
        "clinical tests": [],
        "other symptoms": []
      },
      "freq": "common"
    },
    {
      "name": "Irritation (urine/feces in the incontinent)",
      "system": "General",
      "redFlag": false,
      "hpi": {
        "onset": [],
        "progression": [],
        "palliate": [],
        "provoke": [],
        "quality": [],
        "timing": [],
        "region": [],
        "radiation": [],
        "severity": [],
        "clinical tests": [],
        "other symptoms": []
      },
      "freq": "common"
    },
    {
      "name": "Dermatitis",
      "system": "General",
      "redFlag": false,
      "hpi": {
        "onset": [],
        "progression": [],
        "palliate": [],
        "provoke": [],
        "quality": [],
        "timing": [],
        "region": [],
        "radiation": [],
        "severity": [],
        "clinical tests": [],
        "other symptoms": []
      },
      "freq": "uncommon"
    },
    {
      "name": "Herpes simplex",
      "system": "General",
      "redFlag": false,
      "hpi": {
        "onset": [],
        "progression": [],
        "palliate": [],
        "provoke": [],
        "quality": [],
        "timing": [],
        "region": [],
        "radiation": [],
        "severity": [],
        "clinical tests": [],
        "other symptoms": []
      },
      "freq": "rare"
    },
    {
      "name": "Strangulated hernia",
      "system": "Internal Scrotal Swellings",
      "redFlag": false,
      "hpi": {
        "onset": [],
        "progression": [],
        "palliate": [],
        "provoke": [],
        "quality": [],
        "timing": [],
        "region": [],
        "radiation": [],
        "severity": [],
        "clinical tests": [],
        "other symptoms": []
      },
      "freq": "common"
    },
    {
      "name": "Testicular torsion",
      "system": "Internal Scrotal Swellings",
      "redFlag": false,
      "hpi": {
        "onset": [],
        "progression": [],
        "palliate": [],
        "provoke": [],
        "quality": [],
        "timing": [],
        "region": [],
        "radiation": [],
        "severity": [],
        "clinical tests": [],
        "other symptoms": []
      },
      "freq": "common"
    },
    {
      "name": "Epididymo-orchitis",
      "system": "Internal Scrotal Swellings",
      "redFlag": false,
      "hpi": {
        "onset": [],
        "progression": [],
        "palliate": [],
        "provoke": [],
        "quality": [],
        "timing": [],
        "region": [],
        "radiation": [],
        "severity": [],
        "clinical tests": [],
        "other symptoms": []
      },
      "freq": "common"
    },
    {
      "name": "Torsion of testicular appendage",
      "system": "Internal Scrotal Swellings",
      "redFlag": false,
      "hpi": {
        "onset": [],
        "progression": [],
        "palliate": [],
        "provoke": [],
        "quality": [],
        "timing": [],
        "region": [],
        "radiation": [],
        "severity": [],
        "clinical tests": [],
        "other symptoms": []
      },
      "freq": "uncommon"
    },
    {
      "name": "Hematocele",
      "system": "Internal Scrotal Swellings",
      "redFlag": false,
      "hpi": {
        "onset": [],
        "progression": [],
        "palliate": [],
        "provoke": [],
        "quality": [],
        "timing": [],
        "region": [],
        "radiation": [],
        "severity": [],
        "clinical tests": [],
        "other symptoms": []
      },
      "freq": "uncommon"
    },
    {
      "name": "Varicocele",
      "system": "Internal Scrotal Swellings",
      "redFlag": false,
      "hpi": {
        "onset": [],
        "progression": [],
        "palliate": [],
        "provoke": [],
        "quality": [],
        "timing": [],
        "region": [],
        "radiation": [],
        "severity": [],
        "clinical tests": [],
        "other symptoms": []
      },
      "freq": "uncommon"
    },
    {
      "name": "Groin strain",
      "system": "Referred",
      "redFlag": false,
      "hpi": {
        "onset": [],
        "progression": [],
        "palliate": [],
        "provoke": [],
        "quality": [],
        "timing": [],
        "region": [],
        "radiation": [],
        "severity": [],
        "clinical tests": [],
        "other symptoms": []
      },
      "freq": "common"
    },
    {
      "name": "Ilioinguinal nerve entrapment after hernia repair",
      "system": "Referred",
      "redFlag": false,
      "hpi": {
        "onset": [],
        "progression": [],
        "palliate": [],
        "provoke": [],
        "quality": [],
        "timing": [],
        "region": [],
        "radiation": [],
        "severity": [],
        "clinical tests": [],
        "other symptoms": []
      },
      "freq": "uncommon"
    },
    {
      "name": "Idiopathic cord neuralgia",
      "system": "Referred",
      "redFlag": false,
      "hpi": {
        "onset": [],
        "progression": [],
        "palliate": [],
        "provoke": [],
        "quality": [],
        "timing": [],
        "region": [],
        "radiation": [],
        "severity": [],
        "clinical tests": [],
        "other symptoms": []
      },
      "freq": "rare"
    },
    {
      "name": "Spinal nerve irritation",
      "system": "Referred",
      "redFlag": false,
      "hpi": {
        "onset": [],
        "progression": [],
        "palliate": [],
        "provoke": [],
        "quality": [],
        "timing": [],
        "region": [],
        "radiation": [],
        "severity": [],
        "clinical tests": [],
        "other symptoms": []
      },
      "freq": "rare"
    }
  ],
  "sources": {
    "index_keys": [
      "Scrotal pain"
    ],
    "index_type": "clinical"
  },
  "symptoms": {}
}