{
  "presentation": "Cyanosis",
  "items": [
    {
      "name": "Severe respiratory disease",
      "system": "Decreased Oxygen Saturation",
      "redFlag": false,
      "hpi": {
        "onset": [],
        "progression": [],
        "palliate": [],
        "provoke": [],
        "quality": [],
        "timing": [],
        "region": [],
        "radiation": [],
        "severity": [],
        "clinical tests": [],
        "other symptoms": []
      },
      "freq": "common"
    },
    {
      "name": "Pulmonary oedema",
      "system": "Decreased Oxygen Saturation",
      "redFlag": false,
      "hpi": {
        "onset": [],
        "progression": [],
        "palliate": [],
        "provoke": [],
        "quality": [],
        "timing": [],
        "region": [],
        "radiation": [],
        "severity": [],
        "clinical tests": [],
        "other symptoms": []
      },
      "freq": "common"
    },
    {
      "name": "Pulmonary embolism",
      "system": "Decreased Oxygen Saturation",
      "redFlag": false,
      "hpi": {
        "onset": [],
        "progression": [],
        "palliate": [],
        "provoke": [],
        "quality": [],
        "timing": [],
        "region": [],
        "radiation": [],
        "severity": [],
        "clinical tests": [],
        "other symptoms": []
      },
      "freq": "common"
    },
    {
      "name": "Congenital cyanotic heart disease",
      "system": "Decreased Oxygen Saturation",
      "redFlag": false,
      "hpi": {
        "onset": [],
        "progression": [],
        "palliate": [],
        "provoke": [],
        "quality": [],
        "timing": [],
        "region": [],
        "radiation": [],
        "severity": [],
        "clinical tests": [],
        "other symptoms": []
      },
      "freq": "common"
    },
    {
      "name": "Methemoglobinemia",
      "system": "Abnormal Haemoglobin",
      "redFlag": false,
      "hpi": {
        "onset": [],
        "progression": [],
        "palliate": [],
        "provoke": [],
        "quality": [],
        "timing": [],
        "region": [],
        "radiation": [],
        "severity": [],
        "clinical tests": [],
        "other symptoms": []
      },
      "freq": "rare"
    },
    {
      "name": "Sulphemoglobinemia",
      "system": "Abnormal Haemoglobin",
      "redFlag": false,
      "hpi": {
        "onset": [],
        "progression": [],
        "palliate": [],
        "provoke": [],
        "quality": [],
        "timing": [],
        "region": [],
        "radiation": [],
        "severity": [],
        "clinical tests": [],
        "other symptoms": []
      },
      "freq": "rare"
    },
    {
      "name": "All causes of central cyanosis",
      "system": "Peripheral Cyanosis",
      "redFlag": false,
      "hpi": {
        "onset": [],
        "progression": [],
        "palliate": [],
        "provoke": [],
        "quality": [],
        "timing": [],
        "region": [],
        "radiation": [],
        "severity": [],
        "clinical tests": [],
        "other symptoms": []
      },
      "freq": "common"
    },
    {
      "name": "Cold exposure",
      "system": "Peripheral Cyanosis",
      "redFlag": false,
      "hpi": {
        "onset": [],
        "progression": [],
        "palliate": [],
        "provoke": [],
        "quality": [],
        "timing": [],
        "region": [],
        "radiation": [],
        "severity": [],
        "clinical tests": [],
        "other symptoms": []
      },
      "freq": "common"
    },
    {
      "name": "Raynaud\u2019s phenomenon",
      "system": "Peripheral Cyanosis",
      "redFlag": false,
      "hpi": {
        "onset": [],
        "progression": [],
        "palliate": [],
        "provoke": [],
        "quality": [],
        "timing": [],
        "region": [],
        "radiation": [],
        "severity": [],
        "clinical tests": [],
        "other symptoms": []
      },
      "freq": "common"
    },
    {
      "name": "Arterial occlusion",
      "system": "Peripheral Cyanosis",
      "redFlag": false,
      "hpi": {
        "onset": [],
        "progression": [],
        "palliate": [],
        "provoke": [],
        "quality": [],
        "timing": [],
        "region": [],
        "radiation": [],
        "severity": [],
        "clinical tests": [],
        "other symptoms": []
      },
      "freq": "common"
    },
    {
      "name": "Venous occlusion",
      "system": "Peripheral Cyanosis",
      "redFlag": false,
      "hpi": {
        "onset": [],
        "progression": [],
        "palliate": [],
        "provoke": [],
        "quality": [],
        "timing": [],
        "region": [],
        "radiation": [],
        "severity": [],
        "clinical tests": [],
        "other symptoms": []
      },
      "freq": "uncommon"
    },
    {
      "name": "Acrocyanosis",
      "system": "Peripheral Cyanosis",
      "redFlag": false,
      "hpi": {
        "onset": [],
        "progression": [],
        "palliate": [],
        "provoke": [],
        "quality": [],
        "timing": [],
        "region": [],
        "radiation": [],
        "severity": [],
        "clinical tests": [],
        "other symptoms": []
      },
      "freq": "uncommon"
    }
  ],
  "sources": {
    "index_keys": [
      "Cyanosis"
    ],
    "index_type": "clinical"
  },
  "symptoms": {}
}